MANIFEST.in
README.md
README.rst
setup.cfg
setup.py
src/demo.py
src/subset_nwm_netcdf/__init__.py
src/subset_nwm_netcdf/base.py
src/subset_nwm_netcdf/configs.py
src/subset_nwm_netcdf/create_symbolic.py
src/subset_nwm_netcdf/merge.py
src/subset_nwm_netcdf/query.py
src/subset_nwm_netcdf/subset.py
src/subset_nwm_netcdf.egg-info/PKG-INFO
src/subset_nwm_netcdf.egg-info/SOURCES.txt
src/subset_nwm_netcdf.egg-info/dependency_links.txt
src/subset_nwm_netcdf.egg-info/not-zip-safe
src/subset_nwm_netcdf.egg-info/requires.txt
src/subset_nwm_netcdf.egg-info/top_level.txt
src/subset_nwm_netcdf/static/data/TwoMileCreek/TwoMileCreek_poly.dbf
src/subset_nwm_netcdf/static/data/TwoMileCreek/TwoMileCreek_poly.prj
src/subset_nwm_netcdf/static/data/TwoMileCreek/TwoMileCreek_poly.shp
src/subset_nwm_netcdf/static/data/TwoMileCreek/TwoMileCreek_poly.shx
src/subset_nwm_netcdf/static/data/tests/Sphere_Lambert_Conformal_Conic.prj
src/subset_nwm_netcdf/static/data/tests/nwm.t00z.analysis_assim.land.tm00.conus_index.cdl
src/subset_nwm_netcdf/static/data/tests/nwm.t00z.analysis_assim.land.tm00.conus_xy.cdl
src/subset_nwm_netcdf/static/data/tests/nwm.t00z.analysis_assim.terrain_rt.tm00.conus_index.cdl
src/subset_nwm_netcdf/static/data/tests/nwm.t00z.analysis_assim.terrain_rt.tm00.conus_xy.cdl
src/subset_nwm_netcdf/static/data/twomile_custom_projection/TwoMileCreek.cpg
src/subset_nwm_netcdf/static/data/twomile_custom_projection/TwoMileCreek.dbf
src/subset_nwm_netcdf/static/data/twomile_custom_projection/TwoMileCreek.prj
src/subset_nwm_netcdf/static/data/twomile_custom_projection/TwoMileCreek.sbn
src/subset_nwm_netcdf/static/data/twomile_custom_projection/TwoMileCreek.sbx
src/subset_nwm_netcdf/static/data/twomile_custom_projection/TwoMileCreek.shp
src/subset_nwm_netcdf/static/data/twomile_custom_projection/TwoMileCreek.shp.xml
src/subset_nwm_netcdf/static/data/twomile_custom_projection/TwoMileCreek.shx
src/subset_nwm_netcdf/static/data/utah/utah_utm_nad83_zone_12.dbf
src/subset_nwm_netcdf/static/data/utah/utah_utm_nad83_zone_12.prj
src/subset_nwm_netcdf/static/data/utah/utah_utm_nad83_zone_12.shp
src/subset_nwm_netcdf/static/data/utah/utah_utm_nad83_zone_12.shp.xml
src/subset_nwm_netcdf/static/data/utah/utah_utm_nad83_zone_12.shx
