Metadata-Version: 1.0
Name: subset-nwm-netcdf
Version: 1.2.3
Summary: Subset National Water Model (NWM) NetCDF
Home-page: https://github.com/zhiyuli/subset_nwm_netcdf
Author: Zhiyu/Drew Li
Author-email: zyli2004@gmail.com
License: BSD-2
Platform: UNKNOWN
